LICENSE
MANIFEST.in
README.rst
esclient.py
setup.py
ESClient.egg-info/PKG-INFO
ESClient.egg-info/SOURCES.txt
ESClient.egg-info/dependency_links.txt
ESClient.egg-info/requires.txt
ESClient.egg-info/top_level.txt
bin/esdump
bin/esimport