Metadata-Version: 1.1
Name: ESClient
Version: 0.5.7
Summary: A lightweight Python client for ElasticSearch, including a dump and import tool for indexes
Home-page: https://github.com/eriky/ESClient
Author: Erik-Jan van Baaren
Author-email: erikjan@gmail.com
License: New BSD license
Keywords: elasticsearch
Platform: UNKNOWN
Classifier: Development Status :: 4 - Beta
Classifier: Environment :: Web Environment
Classifier: Intended Audience :: Developers
Classifier: License :: OSI Approved :: BSD License
Classifier: Operating System :: OS Independent
Classifier: Programming Language :: Python
Classifier: Topic :: Internet :: WWW/HTTP :: Indexing/Search
